CHANGELOG.txt
LICENSE.txt
MANIFEST.in
README.txt
ez_setup.py
setup.cfg
setup.py
Archiver.egg-info/PKG-INFO
Archiver.egg-info/SOURCES.txt
Archiver.egg-info/dependency_links.txt
Archiver.egg-info/entry_points.txt
Archiver.egg-info/not-zip-safe
Archiver.egg-info/requires.txt
Archiver.egg-info/top_level.txt
archiver/__init__.py
archiver/api.py
archiver/command.py
archiver/helper.py
archiver/test.py
doc/Makefile
doc/index.txt
doc/source/api.rst
doc/source/conf.py
doc/source/index.rst
doc/source/manual.rst
example/README.txt
test/README.txt
test/doc.py
test/test.py