Metadata-Version: 1.0
Name: Archiver
Version: 0.2.2
Summary: Manage files based on their SHA1 hashes
Home-page: http://jimmyg.org/work/code/archiver/index.html
Author: James Gardner
Author-email: james@<package hompage URL>
License: GNU AGPLv3
Platform: UNKNOWN
Classifier: Development Status :: 3 - Alpha
Classifier: License :: OSI Approved :: GNU Affero General Public License v3
Classifier: Programming Language :: Python
